{
    "genuses": {
        "$codex_ent_aleoids_genus_name;":       { "ccr": 150},
        "$codex_ent_sphere_genus_name;":        { "ccr": 100, "comment": "anemone, guesswork"},
        "$codex_ent_bacterial_genus_name;":     { "ccr": 500},
        "$codex_ent_cone_genus_name;":          { "ccr": 100, "comment": "bark mound, guesswork"},
        "$codex_ent_seed_genus_name;":          { "ccr": 100, "commment": "brain tree, guesswork"},
        "$codex_ent_cactoid_genus_name;":       { "ccr": 300},
        "$codex_ent_clypeus_genus_name;":       { "ccr": 150},
        "$codex_ent_conchas_genus_name;":       { "ccr": 150},
        "$codex_ent_electricae_genus_name;":    { "ccr": 1000},
        "$codex_ent_fonticulus_genus_name;":    { "ccr": 500},
        "$codex_ent_shrubs_genus_name;":        { "ccr": 150, "comment": "frutexa"},
        "$codex_ent_fumerolas_genus_name;":     { "ccr": 100},
        "$codex_ent_fungoids_genus_name;":      { "ccr": 300},
        "$codex_ent_osseus_genus_name;":        { "ccr": 800},
        "$codex_ent_recepta_genus_name;":       { "ccr": 150},
        "$codex_ent_tube_genus_name;":          { "ccr": 100, "comment": "sinuous tuber, guesswork"},
        "$codex_ent_stratum_genus_name;":       { "ccr": 500},
        "$codex_ent_tubus_genus_name;":         { "ccr": 800},
        "$codex_ent_tussocks_genus_name;":      { "ccr": 200},
        "$codex_ent_ground_struct_ice_name;":   { "ccr": 100},
        "$codex_ent_ingensradices_genus_name;": { "ccr": 15, "comment": "radicoida"}
    },
    "species": {
        "$codex_ent_aleoids_01_name;": { "credits": 7252500, "name": "Aleoida Arcus"},
        "$codex_ent_aleoids_02_name;": { "credits": 6284600, "name": "Aleoida Coronamus"},
        "$codex_ent_aleoids_05_name;": { "credits": 12934900, "name": "Aleoida Gravis"},
        "$codex_ent_aleoids_04_name;": { "credits": 3385200, "name": "Aleoida Laminiae"},
        "$codex_ent_aleoids_03_name;": { "credits": 3385200, "name": "Aleoida Spica"},
        
        "$codex_ent_bacterial_04_name;": { "credits": 1000000, "name": "Bacterium Acies"},
        "$codex_ent_bacterial_06_name;": { "credits": 1658500, "name": "Bacterium Alcyoneum"},
        "$codex_ent_bacterial_01_name;": { "credits": 1000000, "name": "Bacterium Aurasus"},
        "$codex_ent_bacterial_10_name;": { "credits": 1152500, "name": "Bacterium Bullaris"},
        "$codex_ent_bacterial_12_name;": { "credits": 1689800, "name": "Bacterium Cerbrus"},
        "$codex_ent_bacterial_08_name;": { "credits": 8418000, "name": "Bacterium Informem"},
        "$codex_ent_bacterial_02_name;": { "credits": 5289900, "name": "Bacterium Nebulus"},
        "$codex_ent_bacterial_11_name;": { "credits": 4638900, "name": "Bacterium Omentum"},
        "$codex_ent_bacterial_03_name;": { "credits": 4934500, "name": "Bacterium Scopulum"},
        "$codex_ent_bacterial_07_name;": { "credits": 1949000, "name": "Bacterium Tela "},
        "$codex_ent_bacterial_13_name;": { "credits": 3897000, "name": "Bacterium Verrata"},
        "$codex_ent_bacterial_05_name;": { "credits": 1000000, "name": "Bacterium Vesicula"},
        "$codex_ent_bacterial_09_name;": { "credits": 7774700, "name": "Bacterium Volu"},
        
        "$codex_ent_cactoid_01_name;": { "credits": 3667600, "name": "Cactoida Cortexum"},
        "$codex_ent_cactoid_02_name;": { "credits": 2483600, "name": "Cactoida Lapis"},
        "$codex_ent_cactoid_05_name;": { "credits": 2483600, "name": "Cactoida Peperatis"},
        "$codex_ent_cactoid_04_name;": { "credits": 3667600, "name": "Cactoida Pullulanta"},
        "$codex_ent_cactoid_03_name;": { "credits": 16202800, "name": "Cactoida Vermis"},
        
        "$codex_ent_clypeus_01_name;": { "credits": 8418000, "name": "Clypeus Lacrimam"},
        "$codex_ent_clypeus_02_name;": { "credits": 11873200, "name": "Clypeus Margaritus"},
        "$codex_ent_clypeus_03_name;": { "credits": 16202800, "name": "Clypeus Speculumi"},
        
        "$codex_ent_conchas_02_name;": { "credits": 7774700, "name": "Concha Aureolas"},
        "$codex_ent_conchas_04_name;": { "credits": 19010800, "name": "Concha Biconcavis"},
        "$codex_ent_conchas_03_name;": { "credits": 2352400, "name": "Concha Labiata"},
        "$codex_ent_conchas_01_name;": { "credits": 4572400, "name": "Concha Renibus"},
        
        "$codex_ent_electricae_01_name;": { "credits": 6284600, "name": "Electricae Pluma"},
        "$codex_ent_electricae_02_name;": { "credits": 6284600, "name": "Electricae Radialem"},
        
        "$codex_ent_fonticulus_02_name;": { "credits": 1000000, "name": "Fonticulua Campestris"},
        "$codex_ent_fonticulus_06_name;": { "credits": 1804100, "name": "Fonticulua Digitos"},
        "$codex_ent_fonticulus_05_name;": { "credits": 20000000, "name": "Fonticulua Fluctus"},
        "$codex_ent_fonticulus_04_name;": { "credits": 3111000, "name": "Fonticulua Lapida"},
        "$codex_ent_fonticulus_01_name;": { "credits": 19010800, "name": "Fonticulua Segmentatus"},
        "$codex_ent_fonticulus_03_name;": { "credits": 5727600, "name": "Fonticulua Upupam"},
        
        "$codex_ent_shrubs_02_name;": { "credits": 7774700, "name": "Frutexa Acus"},
        "$codex_ent_shrubs_07_name;": { "credits": 1639800, "name": "Frutexa Collum"},
        "$codex_ent_shrubs_05_name;": { "credits": 1632500, "name": "Frutexa Fera"},
        "$codex_ent_shrubs_01_name;": { "credits": 1808900, "name": "Frutexa Flabellum"},
        "$codex_ent_shrubs_04_name;": { "credits": 10326000, "name": "Frutexa Flammasis"},
        "$codex_ent_shrubs_03_name;": { "credits": 1632500, "name": "Frutexa Metallicum"},
        "$codex_ent_shrubs_06_name;": { "credits": 5988000, "name": "Frutexa Sponsae"},
        
        "$codex_ent_fumerolas_04_name;": { "credits": 6284600, "name": "Fumerola Aquatis"},
        "$codex_ent_fumerolas_01_name;": { "credits": 6284600, "name": "Fumerola Carbosis"},
        "$codex_ent_fumerolas_02_name;": { "credits": 16202800, "name": "Fumerola Extremus"},
        "$codex_ent_fumerolas_03_name;": { "credits": 7500900, "name": "Fumerola Nitris"},
        
        "$codex_ent_fungoids_03_name;": { "credits": 3703200, "name": "Fungoida Bullarum"},
        "$codex_ent_fungoids_04_name;": { "credits": 3330300, "name": "Fungoida Gelata"},
        "$codex_ent_fungoids_01_name;": { "credits": 1670100, "name": "Fungoida Setisis"},
        "$codex_ent_fungoids_02_name;": { "credits": 2680300, "name": "Fungoida Stabitis"},
        
        "$codex_ent_osseus_05_name;": { "credits": 1483000, "name": "Osseus Cornibus"},
        "$codex_ent_osseus_02_name;": { "credits": 12934900, "name": "Osseus Discus"},
        "$codex_ent_osseus_01_name;": { "credits": 4027800, "name": "Osseus Fractus"},
        "$codex_ent_osseus_06_name;": { "credits": 9739000, "name": "Osseus Pellebantus"},
        "$codex_ent_osseus_04_name;": { "credits": 3156300, "name": "Osseus Pumice"},
        "$codex_ent_osseus_03_name;": { "credits": 2404700, "name": "Osseus Spiralis"},
        
        "$codex_ent_recepta_03_name;": { "credits": 14313700, "name": "Recepta Conditivus"},
        "$codex_ent_recepta_02_name;": { "credits": 16202800, "name": "Recepta Deltahedronix"},
        "$codex_ent_recepta_01_name;": { "credits": 12934900, "name": "Recepta Umbrux"},
        
        "$codex_ent_stratum_04_name;": { "credits": 2448900, "name": "Stratum Araneamus"},
        "$codex_ent_stratum_06_name;": { "credits": 16202800, "name": "Stratum Cucumisis"},
        "$codex_ent_stratum_01_name;": { "credits": 2448900, "name": "Stratum Excutitus"},
        "$codex_ent_stratum_08_name;": { "credits": 2637500, "name": "Stratum Frigus"},
        "$codex_ent_stratum_03_name;": { "credits": 2788300, "name": "Stratum Laminamus"},
        "$codex_ent_stratum_05_name;": { "credits": 1362000, "name": "Stratum Limaxus"},
        "$codex_ent_stratum_02_name;": { "credits": 1362000, "name": "Stratum Paleas"},
        "$codex_ent_stratum_07_name;": { "credits": 19010800, "name": "Stratum Tectonicas"},
        
        "$codex_ent_tubus_03_name;": { "credits": 11873200, "name": "Tubus Cavas"},
        "$codex_ent_tubus_05_name;": { "credits": 7774700, "name": "Tubus Compagibus"},
        "$codex_ent_tubus_01_name;": { "credits": 2415500, "name": "Tubus Conifer"},
        "$codex_ent_tubus_04_name;": { "credits": 2637500, "name": "Tubus Rosarium"},
        "$codex_ent_tubus_02_name;": { "credits": 5727600, "name": "Tubus Sororibus"},
        
        "$codex_ent_tussocks_08_name;": { "credits": 3252500, "name": "Tussock Albata"},
        "$codex_ent_tussocks_15_name;": { "credits": 7025800, "name": "Tussock Capillum"},
        "$codex_ent_tussocks_11_name;": { "credits": 3472400, "name": "Tussock Caputus"},
        "$codex_ent_tussocks_05_name;": { "credits": 1766600, "name": "Tussock Catena"},
        "$codex_ent_tussocks_04_name;": { "credits": 1766600, "name": "Tussock Cultro"},
        "$codex_ent_tussocks_10_name;": { "credits": 1766600, "name": "Tussock Divisa"},
        "$codex_ent_tussocks_03_name;": { "credits": 1849000, "name": "Tussock Ignis"},
        "$codex_ent_tussocks_01_name;": { "credits": 5853800, "name": "Tussock Pennata"},
        "$codex_ent_tussocks_06_name;": { "credits": 1000000, "name": "Tussock Pennatis"},
        "$codex_ent_tussocks_09_name;": { "credits": 1000000, "name": "Tussock Propagito"},
        "$codex_ent_tussocks_07_name;": { "credits": 4447100, "name": "Tussock Serrati"},
        "$codex_ent_tussocks_13_name;": { "credits": 19010800, "name": "Tussock Stigmasis"},
        "$codex_ent_tussocks_12_name;": { "credits": 7774700, "name": "Tussock Triticum"},
        "$codex_ent_tussocks_02_name;": { "credits": 3227700, "name": "Tussock Ventusa"},
        "$codex_ent_tussocks_14_name;": { "credits": 14313700, "name": "Tussock Virgam"},

        "$codex_ent_ingensradices_unicus_name;": { "credits": 119037, "name": "Radicoida Unicus"}
    },
    "genuses_int_names": {
        "aleoids": "$codex_ent_aleoids_genus_name;",
        "anemone": "$codex_ent_sphere_genus_name;",
        "bacterium": "$codex_ent_bacterial_genus_name;",
        "bark mound": "$codex_ent_cone_genus_name;",
        "seed": "$codex_ent_seed_genus_name;",
        "cactoids": "$codex_ent_cactoid_genus_name;",
        "clypeus": "$codex_ent_clypeus_genus_name;",
        "conchas": "$codex_ent_conchas_genus_name;",
        "electricae": "$codex_ent_electricae_genus_name;",
        "fonticulus": "$codex_ent_fonticulus_genus_name;",
        "shrubs": "$codex_ent_shrubs_genus_name;",
        "fumerolas": "$codex_ent_fumerolas_genus_name;",
        "fungoids": "$codex_ent_fungoids_genus_name;",
        "osseus": "$codex_ent_osseus_genus_name;",
        "recepta": "$codex_ent_recepta_genus_name;",
        "sinuous tuber": "$codex_ent_tube_genus_name;",
        "stratum": "$codex_ent_stratum_genus_name;",
        "tubus": "$codex_ent_tubus_genus_name;",
        "tussocks": "$codex_ent_tussocks_genus_name;",
        "crystalline shard": "$codex_ent_ground_struct_ice_name;",
        "amphora": "$codex_ent_vents_name;",
        "radicoida": "$codex_ent_ingensradices_genus_name;"
    },
    "species_int_names": {
        "aleoida arcus": "$codex_ent_aleoids_01_name;",
        "aleoida coronamus": "$codex_ent_aleoids_02_name;",
        "aleoida gravis": "$codex_ent_aleoids_05_name;",
        "aleoida laminiae": "$codex_ent_aleoids_04_name;",
        "aleoida spica": "$codex_ent_aleoids_03_name;",
            
        "bacterium acies": "$codex_ent_bacterial_04_name;",
        "bacterium alcyoneum": "$codex_ent_bacterial_06_name;",
        "bacterium aurasus": "$codex_ent_bacterial_01_name;",
        "bacterium bullaris": "$codex_ent_bacterial_10_name;",
        "bacterium cerbrus": "$codex_ent_bacterial_12_name;",
        "bacterium informem": "$codex_ent_bacterial_08_name;",
        "bacterium nebulus": "$codex_ent_bacterial_02_name;",
        "bacterium omentum": "$codex_ent_bacterial_11_name;",
        "bacterium scopulum": "$codex_ent_bacterial_03_name;",
        "bacterium tela ": "$codex_ent_bacterial_07_name;",
        "bacterium verrata": "$codex_ent_bacterial_13_name;",
        "bacterium vesicula": "$codex_ent_bacterial_05_name;",
        "bacterium volu": "$codex_ent_bacterial_09_name;",
            
        "cactoida cortexum": "$codex_ent_cactoid_01_name;",
        "cactoida lapis": "$codex_ent_cactoid_02_name;",
        "cactoida peperatis": "$codex_ent_cactoid_05_name;",
        "cactoida pullulanta": "$codex_ent_cactoid_04_name;",
        "cactoida vermis": "$codex_ent_cactoid_03_name;",
            
        "clypeus lacrimam": "$codex_ent_clypeus_01_name;",
        "clypeus margaritus": "$codex_ent_clypeus_02_name;",
        "clypeus speculumi": "$codex_ent_clypeus_03_name;",
            
        "concha aureolas": "$codex_ent_conchas_02_name;",
        "concha biconcavis": "$codex_ent_conchas_04_name;",
        "concha labiata": "$codex_ent_conchas_03_name;",
        "concha renibus": "$codex_ent_conchas_01_name;",
            
        "electricae pluma": "$codex_ent_electricae_01_name;",
        "electricae radialem": "$codex_ent_electricae_02_name;",
            
        "fonticulua campestris": "$codex_ent_fonticulus_02_name;",
        "fonticulua digitos": "$codex_ent_fonticulus_06_name;",
        "fonticulua fluctus": "$codex_ent_fonticulus_05_name;",
        "fonticulua lapida": "$codex_ent_fonticulus_04_name;",
        "fonticulua segmentatus": "$codex_ent_fonticulus_01_name;",
        "fonticulua upupam": "$codex_ent_fonticulus_03_name;",
            
        "frutexa acus": "$codex_ent_shrubs_02_name;",
        "frutexa collum": "$codex_ent_shrubs_07_name;",
        "frutexa fera": "$codex_ent_shrubs_05_name;",
        "frutexa flabellum": "$codex_ent_shrubs_01_name;",
        "frutexa flammasis": "$codex_ent_shrubs_04_name;",
        "frutexa metallicum": "$codex_ent_shrubs_03_name;",
        "frutexa sponsae": "$codex_ent_shrubs_06_name;",
            
        "fumerola aquatis": "$codex_ent_fumerolas_04_name;",
        "fumerola carbosis": "$codex_ent_fumerolas_01_name;",
        "fumerola extremus": "$codex_ent_fumerolas_02_name;",
        "fumerola nitris": "$codex_ent_fumerolas_03_name;",
            
        "fungoida bullarum": "$codex_ent_fungoids_03_name;",
        "fungoida gelata": "$codex_ent_fungoids_04_name;",
        "fungoida setisis": "$codex_ent_fungoids_01_name;",
        "fungoida stabitis": "$codex_ent_fungoids_02_name;",
            
        "osseus cornibus": "$codex_ent_osseus_05_name;",
        "osseus discus": "$codex_ent_osseus_02_name;",
        "osseus fractus": "$codex_ent_osseus_01_name;",
        "osseus pellebantus": "$codex_ent_osseus_06_name;",
        "osseus pumice": "$codex_ent_osseus_04_name;",
        "osseus spiralis": "$codex_ent_osseus_03_name;",
            
        "recepta conditivus": "$codex_ent_recepta_03_name;",
        "recepta deltahedronix": "$codex_ent_recepta_02_name;",
        "recepta umbrux": "$codex_ent_recepta_01_name;",
            
        "stratum araneamus": "$codex_ent_stratum_04_name;",
        "stratum cucumisis": "$codex_ent_stratum_06_name;",
        "stratum excutitus": "$codex_ent_stratum_01_name;",
        "stratum frigus": "$codex_ent_stratum_08_name;",
        "stratum laminamus": "$codex_ent_stratum_03_name;",
        "stratum limaxus": "$codex_ent_stratum_05_name;",
        "stratum paleas": "$codex_ent_stratum_02_name;",
        "stratum tectonicas": "$codex_ent_stratum_07_name;",
            
        "tubus cavas": "$codex_ent_tubus_03_name;",
        "tubus compagibus": "$codex_ent_tubus_05_name;",
        "tubus conifer": "$codex_ent_tubus_01_name;",
        "tubus rosarium": "$codex_ent_tubus_04_name;",
        "tubus sororibus": "$codex_ent_tubus_02_name;",
            
        "tussock albata": "$codex_ent_tussocks_08_name;",
        "tussock capillum": "$codex_ent_tussocks_15_name;",
        "tussock caputus": "$codex_ent_tussocks_11_name;",
        "tussock catena": "$codex_ent_tussocks_05_name;",
        "tussock cultro": "$codex_ent_tussocks_04_name;",
        "tussock divisa": "$codex_ent_tussocks_10_name;",
        "tussock ignis": "$codex_ent_tussocks_03_name;",
        "tussock pennata": "$codex_ent_tussocks_01_name;",
        "tussock pennatis": "$codex_ent_tussocks_06_name;",
        "tussock propagito": "$codex_ent_tussocks_09_name;",
        "tussock serrati": "$codex_ent_tussocks_07_name;",
        "tussock stigmasis": "$codex_ent_tussocks_13_name;",
        "tussock triticum": "$codex_ent_tussocks_12_name;",
        "tussock ventusa": "$codex_ent_tussocks_02_name;",
        "tussock virgam": "$codex_ent_tussocks_14_name;",

        "radicoida unicus": "$codex_ent_ingensradices_unicus_name;"
    }
}